environmental_risk_metrics/__init__.py
environmental_risk_metrics/base.py
environmental_risk_metrics/exceptions.py
environmental_risk_metrics/py.typed
environmental_risk_metrics/legends/__init__.py
environmental_risk_metrics/legends/land_use_change.py
environmental_risk_metrics/metrics/endangered_species.py
environmental_risk_metrics/metrics/land_use_change.py
environmental_risk_metrics/metrics/landsat.py
environmental_risk_metrics/metrics/ndvi.py
environmental_risk_metrics/metrics/protected_areas.py
environmental_risk_metrics/metrics/sentinel2_items.py
environmental_risk_metrics/metrics/social_indices.py
environmental_risk_metrics/metrics/soil_organic_carbon.py
environmental_risk_metrics/metrics/soil_types.py
environmental_risk_metrics/resources/global_witness_led_10-10-24.csv
environmental_risk_metrics/resources/ramsar_sites.parquet
environmental_risk_metrics/resources/soil_types.json
environmental_risk_metrics/resources/world_countries_geojson.gpkg
environmental_risk_metrics/utils/__init__.py
environmental_risk_metrics/utils/metric_calculator.py
environmental_risk_metrics/utils/planetary_computer.py
environmental_risk_metrics-0.3.5.dist-info/METADATA
environmental_risk_metrics-0.3.5.dist-info/WHEEL
environmental_risk_metrics-0.3.5.dist-info/licenses/LICENSE
environmental_risk_metrics-0.3.5.dist-info/RECORD
