Metadata-Version: 2.4
Name: environmental-risk-metrics
Version: 0.3.5
Summary: Calculate environmentalrisk metrics for a given polygon
Author-email: Thimm Zwiener <zwiener@gmail.com>, Thimm Zwiener <thimm@regenrate.com>
License-File: LICENSE
Requires-Python: >=3.10
Requires-Dist: beautifulsoup4>=4.12.0
Requires-Dist: geopandas>=1.0.1
Requires-Dist: geopy>=2.4.1
Requires-Dist: imageio>=2.31.0
Requires-Dist: ipython>=8.0.0
Requires-Dist: leafmap>=0.42.5
Requires-Dist: matplotlib>=3.7.0
Requires-Dist: numpy>=1.24.0
Requires-Dist: odc-stac>=0.3.10
Requires-Dist: pandas>=2.0.0
Requires-Dist: planetary-computer>=1.0.0
Requires-Dist: pyarrow>=18.1.0
Requires-Dist: pygbif>=0.6.5
Requires-Dist: pyproj>=3.5.0
Requires-Dist: pystac-client>=0.8.5
Requires-Dist: rasterstats>=0.20.0
Requires-Dist: requests>=2.31.0
Requires-Dist: rioxarray>=0.18.1
Requires-Dist: shapely>=2.0.0
Requires-Dist: tenacity>=8.2.0
Requires-Dist: tqdm>=4.65.0
Requires-Dist: xarray>=2023.1.0
